[
    {
        "centroid": [
            74.3604575688654,
            31.49094099164607
        ],
        "value": 577,
        "advantage": 0,
        "ps": "1",
        "winner": "pti"
    },
    {
        "centroid": [
            74.27764924706726,
            31.50885601699094
        ],
        "value": 411,
        "advantage": 0,
        "ps": "2",
        "winner": "pti"
    },
    {
        "centroid": [
            74.34444656526016,
            31.5007864197971
        ],
        "value": 924,
        "advantage": 0,
        "ps": "3",
        "winner": "pti"
    },
    {
        "centroid": [
            74.3499121462826,
            31.52691063312634
        ],
        "value": 970,
        "advantage": 400,
        "ps": "7",
        "winner": "est"
    },
    {
        "centroid": [
            74.32980777034457,
            31.54354603052873
        ],
        "value": 591,
        "advantage": 0,
        "ps": "8",
        "winner": "pti"
    },
    {
        "centroid": [
            74.33990296313988,
            31.53149707419841
        ],
        "value": 494,
        "advantage": 0,
        "ps": "9",
        "winner": "pti"
    },
    {
        "centroid": [
            74.34430083608169,
            31.54785636906531
        ],
        "value": 471,
        "advantage": 0,
        "ps": "10",
        "winner": "pti"
    },
    {
        "centroid": [
            74.32939148251712,
            31.537948509503515
        ],
        "value": 390,
        "advantage": 0,
        "ps": "11",
        "winner": "pti"
    },
    {
        "centroid": [
            74.32111091917368,
            31.51110463311948
        ],
        "value": 862,
        "advantage": -115,
        "ps": "12",
        "winner": "pti"
    },
    {
        "centroid": [
            74.33503735298059,
            31.53951971975484
        ],
        "value": 550,
        "advantage": 0,
        "ps": "13",
        "winner": "pti"
    },
    {
        "centroid": [
            74.36439198537946,
            31.494044718382888
        ],
        "value": 379,
        "advantage": 0,
        "ps": "14",
        "winner": "pti"
    },
    {
        "centroid": [
            74.28766238137969,
            31.51142496816505
        ],
        "value": 551,
        "advantage": 0,
        "ps": "15",
        "winner": "pti"
    },
    {
        "centroid": [
            74.33419381229493,
            31.556120802166642
        ],
        "value": 1057,
        "advantage": 413,
        "ps": "16",
        "winner": "est"
    },
    {
        "centroid": [
            74.3093021329753,
            31.47694661403898
        ],
        "value": 1052,
        "advantage": 592,
        "ps": "17",
        "winner": "est"
    },
    {
        "centroid": [
            74.355355497344,
            31.530674707942044
        ],
        "value": 795,
        "advantage": 0,
        "ps": "18",
        "winner": "pti"
    },
    {
        "centroid": [
            74.34392669646063,
            31.531775797860643
        ],
        "value": 551,
        "advantage": 0,
        "ps": "22",
        "winner": "pti"
    },
    {
        "centroid": [
            74.31349824565352,
            31.52980251835127
        ],
        "value": 924,
        "advantage": 241,
        "ps": "23",
        "winner": "est"
    },
    {
        "centroid": [
            74.33939081618907,
            31.549856385051203
        ],
        "value": 1816,
        "advantage": 1000,
        "ps": "24",
        "winner": "est"
    },
    {
        "centroid": [
            74.35194404328843,
            31.536927222617294
        ],
        "value": 674,
        "advantage": 0,
        "ps": "26",
        "winner": "pti"
    },
    {
        "centroid": [
            74.35226942992271,
            31.49359325350872
        ],
        "value": 602,
        "advantage": 0,
        "ps": "30",
        "winner": "pti"
    },
    {
        "centroid": [
            74.35899339911869,
            31.51030312970269
        ],
        "value": 448,
        "advantage": 0,
        "ps": "31",
        "winner": "pti"
    },
    {
        "centroid": [
            74.36684481790353,
            31.500124482540958
        ],
        "value": 513,
        "advantage": -81,
        "ps": "32",
        "winner": "pti"
    },
    {
        "centroid": [
            74.33256592651709,
            31.531089789774445
        ],
        "value": 1157,
        "advantage": 882,
        "ps": "34",
        "winner": "est"
    },
    {
        "centroid": [
            74.31272512999118,
            31.519946586512273
        ],
        "value": 1555,
        "advantage": 991,
        "ps": "35",
        "winner": "est"
    },
    {
        "centroid": [
            74.36066924118957,
            31.481586592555356
        ],
        "value": 367,
        "advantage": 0,
        "ps": "37",
        "winner": "pti"
    },
    {
        "centroid": [
            74.34833072853093,
            31.53496285385184
        ],
        "value": 360,
        "advantage": -1,
        "ps": "38",
        "winner": "pti"
    },
    {
        "centroid": [
            74.3193380531049,
            31.544227339374146
        ],
        "value": 510,
        "advantage": 279,
        "ps": "40",
        "winner": "est"
    },
    {
        "centroid": [
            74.29983209654412,
            31.513103543787444
        ],
        "value": 432,
        "advantage": 0,
        "ps": "41",
        "winner": "pti"
    },
    {
        "centroid": [
            74.29577637376103,
            31.49532625102322
        ],
        "value": 544,
        "advantage": 0,
        "ps": "44",
        "winner": "pti"
    },
    {
        "centroid": [
            74.3295498219314,
            31.50119967449229
        ],
        "value": 843,
        "advantage": 0,
        "ps": "47",
        "winner": "pti"
    },
    {
        "centroid": [
            74.34358699189427,
            31.505348633722978
        ],
        "value": 755,
        "advantage": 0,
        "ps": "50",
        "winner": "pti"
    },
    {
        "centroid": [
            74.31642345969533,
            31.48087449165266
        ],
        "value": 2026,
        "advantage": 1000,
        "ps": "51",
        "winner": "est"
    },
    {
        "centroid": [
            74.35407092763735,
            31.542593749403498
        ],
        "value": 1816,
        "advantage": 1000,
        "ps": "52",
        "winner": "est"
    },
    {
        "centroid": [
            74.3574842358664,
            31.511545140541934
        ],
        "value": 874,
        "advantage": 0,
        "ps": "53",
        "winner": "pti"
    },
    {
        "centroid": [
            74.32276082780388,
            31.480405042202506
        ],
        "value": 575,
        "advantage": 0,
        "ps": "54",
        "winner": "est"
    },
    {
        "centroid": [
            74.30284313002633,
            31.490168710632997
        ],
        "value": 634,
        "advantage": 0,
        "ps": "55",
        "winner": "est"
    },
    {
        "centroid": [
            74.31709091484375,
            31.535014657842595
        ],
        "value": 377,
        "advantage": 0,
        "ps": "56",
        "winner": "est"
    },
    {
        "centroid": [
            74.35149519450607,
            31.47470030130672
        ],
        "value": 595,
        "advantage": 0,
        "ps": "57",
        "winner": "pti"
    },
    {
        "centroid": [
            74.33021134625325,
            31.514115483746007
        ],
        "value": 1479,
        "advantage": 800,
        "ps": "58",
        "winner": "est"
    },
    {
        "centroid": [
            74.29164002638453,
            31.515096709542068
        ],
        "value": 476,
        "advantage": 0,
        "ps": "59",
        "winner": "pti"
    },
    {
        "centroid": [
            74.31848463430535,
            31.486100790599902
        ],
        "value": 1141,
        "advantage": 700,
        "ps": "60",
        "winner": "est"
    },
    {
        "centroid": [
            74.29829142617221,
            31.500591941157108
        ],
        "value": 627,
        "advantage": 0,
        "ps": "61",
        "winner": "pti"
    },
    {
        "centroid": [
            74.35641010068184,
            31.50451972697724
        ],
        "value": 714,
        "advantage": 0,
        "ps": "62",
        "winner": "pti"
    },
    {
        "centroid": [
            74.3267669874783,
            31.550527805310978
        ],
        "value": 707,
        "advantage": -147,
        "ps": "63",
        "winner": "pti"
    },
    {
        "centroid": [
            74.35176950595438,
            31.468985944931273
        ],
        "value": 642,
        "advantage": 0,
        "ps": "64",
        "winner": "pti"
    },
    {
        "centroid": [
            74.35019858432614,
            31.507192291791476
        ],
        "value": 1460,
        "advantage": 600,
        "ps": "70",
        "winner": "est"
    },
    {
        "centroid": [
            74.3392380663869,
            31.5360123815883
        ],
        "value": 1788,
        "advantage": 913,
        "ps": "71",
        "winner": "est"
    },
    {
        "centroid": [
            74.29634328036917,
            31.49852718291146
        ],
        "value": 897,
        "advantage": 600,
        "ps": "72",
        "winner": "est"
    },
    {
        "centroid": [
            74.33307340360906,
            31.48644020938273
        ],
        "value": 969,
        "advantage": 0,
        "ps": "73",
        "winner": "est"
    },
    {
        "centroid": [
            74.33328565656727,
            31.507763150488135
        ],
        "value": 1521,
        "advantage": 500,
        "ps": "75",
        "winner": "est"
    },
    {
        "centroid": [
            74.3185471367491,
            31.490901003585435
        ],
        "value": 1603,
        "advantage": 681,
        "ps": "77",
        "winner": "est"
    },
    {
        "centroid": [
            74.332055184449,
            31.52128992974056
        ],
        "value": 474,
        "advantage": 0,
        "ps": "79",
        "winner": "pti"
    },
    {
        "centroid": [
            74.33955249647917,
            31.500285385736145
        ],
        "value": 490,
        "advantage": 0,
        "ps": "80",
        "winner": "pti"
    },
    {
        "centroid": [
            74.27434342481862,
            31.511012477175505
        ],
        "value": 725,
        "advantage": 0,
        "ps": "82",
        "winner": "pti"
    },
    {
        "centroid": [
            74.34301328992296,
            31.541127014443937
        ],
        "value": 871,
        "advantage": 0,
        "ps": "85",
        "winner": "pti"
    },
    {
        "centroid": [
            74.31915414346581,
            31.50760770650926
        ],
        "value": 1283,
        "advantage": 700,
        "ps": "88",
        "winner": "est"
    },
    {
        "centroid": [
            74.31903089796367,
            31.49669383767808
        ],
        "value": 480,
        "advantage": 700,
        "ps": "94",
        "winner": "est"
    },
    {
        "centroid": [
            74.32528051543486,
            31.49415774949256
        ],
        "value": 784,
        "advantage": 0,
        "ps": "95",
        "winner": "pti"
    },
    {
        "centroid": [
            74.30169943715741,
            31.476703045034196
        ],
        "value": 791,
        "advantage": 0,
        "ps": "98",
        "winner": "pti"
    },
    {
        "centroid": [
            74.35157205741497,
            31.46628824892815
        ],
        "value": 1451,
        "advantage": 800,
        "ps": "99",
        "winner": "est"
    },
    {
        "centroid": [
            74.34029008301188,
            31.51133410126863
        ],
        "value": 1178,
        "advantage": 1065,
        "ps": "100",
        "winner": "est"
    },
    {
        "centroid": [
            74.34596533511915,
            31.5512961041249
        ],
        "value": 1051,
        "advantage": 600,
        "ps": "101",
        "winner": "est"
    },
    {
        "centroid": [
            74.29980001249822,
            31.496040515747296
        ],
        "value": 907,
        "advantage": 500,
        "ps": "103",
        "winner": "est"
    },
    {
        "centroid": [
            74.34863431093004,
            31.548216526979875
        ],
        "value": 535,
        "advantage": 0,
        "ps": "104",
        "winner": "pti"
    },
    {
        "centroid": [
            74.34433183761232,
            31.509420260835437
        ],
        "value": 524,
        "advantage": 0,
        "ps": "105",
        "winner": "pti"
    },
    {
        "centroid": [
            74.29525438357048,
            31.503686680423254
        ],
        "value": 1233,
        "advantage": 700,
        "ps": "106",
        "winner": "est"
    },
    {
        "centroid": [
            74.35191922464043,
            31.525540898635676
        ],
        "value": 621,
        "advantage": 0,
        "ps": "108",
        "winner": "pti"
    },
    {
        "centroid": [
            74.34852986160514,
            31.513061977215937
        ],
        "value": 968,
        "advantage": 500,
        "ps": "109",
        "winner": "est"
    },
    {
        "centroid": [
            74.32874932733228,
            31.524549819181267
        ],
        "value": 499,
        "advantage": 0,
        "ps": "110",
        "winner": "pti"
    },
    {
        "centroid": [
            74.31935035422549,
            31.52658169250733
        ],
        "value": 1405,
        "advantage": 600,
        "ps": "111",
        "winner": "est"
    },
    {
        "centroid": [
            74.33931158295383,
            31.508053805878372
        ],
        "value": 689,
        "advantage": 0,
        "ps": "112",
        "winner": "pti"
    },
    {
        "centroid": [
            74.34952794053153,
            31.502508824729727
        ],
        "value": 991,
        "advantage": 462,
        "ps": "113",
        "winner": "est"
    },
    {
        "centroid": [
            74.34078161654885,
            31.515733139078613
        ],
        "value": 930,
        "advantage": 500,
        "ps": "114",
        "winner": "est"
    },
    {
        "centroid": [
            74.32207509767258,
            31.514428831267328
        ],
        "value": 712,
        "advantage": 0,
        "ps": "115",
        "winner": "pti"
    },
    {
        "centroid": [
            74.31257485885855,
            31.479829686753785
        ],
        "value": 658,
        "advantage": 0,
        "ps": "116",
        "winner": "pti"
    },
    {
        "centroid": [
            74.32879187487526,
            31.48055948570957
        ],
        "value": 426,
        "advantage": 0,
        "ps": "117",
        "winner": "pti"
    },
    {
        "centroid": [
            74.3409868545233,
            31.49811724110374
        ],
        "value": 317,
        "advantage": 0,
        "ps": "118",
        "winner": "pti"
    },
    {
        "centroid": [
            74.33126358246568,
            31.49566871458189
        ],
        "value": 614,
        "advantage": 0,
        "ps": "120",
        "winner": "pti"
    },
    {
        "centroid": [
            74.35257088429614,
            31.516694918726635
        ],
        "value": 889,
        "advantage": 0,
        "ps": "121",
        "winner": "pti"
    },
    {
        "centroid": [
            74.32700454860834,
            31.483440159427172
        ],
        "value": 675,
        "advantage": 0,
        "ps": "126",
        "winner": "pti"
    },
    {
        "centroid": [
            74.33268984299666,
            31.4826113210143
        ],
        "value": 769,
        "advantage": 0,
        "ps": "128",
        "winner": "pti"
    },
    {
        "centroid": [
            74.35903715102143,
            31.494193079345496
        ],
        "value": 1704,
        "advantage": 0,
        "ps": "129",
        "winner": "pti"
    },
    {
        "centroid": [
            74.35020148141588,
            31.49712789390835
        ],
        "value": 1405,
        "advantage": 600,
        "ps": "135",
        "winner": "est"
    },
    {
        "centroid": [
            74.33582847081915,
            31.512386249949174
        ],
        "value": 565,
        "advantage": 0,
        "ps": "137",
        "winner": "pti"
    },
    {
        "centroid": [
            74.29180596597857,
            31.498299373618238
        ],
        "value": 405,
        "advantage": 0,
        "ps": "138",
        "winner": "pti"
    },
    {
        "centroid": [
            74.28980450704438,
            31.518386565570577
        ],
        "value": 805,
        "advantage": 0,
        "ps": "139",
        "winner": "pti"
    },
    {
        "centroid": [
            74.28435986265113,
            31.515464447296264
        ],
        "value": 537,
        "advantage": 0,
        "ps": "140",
        "winner": "pti"
    },
    {
        "centroid": [
            74.29881837185138,
            31.504399152818927
        ],
        "value": 554,
        "advantage": 0,
        "ps": "141",
        "winner": "pti"
    },
    {
        "centroid": [
            74.294728220809,
            31.50754927663705
        ],
        "value": 698,
        "advantage": 0,
        "ps": "147",
        "winner": "pti"
    },
    {
        "centroid": [
            74.31921955251468,
            31.517806519115766
        ],
        "value": 502,
        "advantage": 0,
        "ps": "148",
        "winner": "pti"
    },
    {
        "centroid": [
            74.35540703642808,
            31.495838409579317
        ],
        "value": 855,
        "advantage": 519,
        "ps": "150",
        "winner": "est"
    },
    {
        "centroid": [
            74.34347157050516,
            31.494725725828374
        ],
        "value": 509,
        "advantage": 0,
        "ps": "151",
        "winner": "pti"
    },
    {
        "centroid": [
            74.34620753174444,
            31.528876822225786
        ],
        "value": 1078,
        "advantage": 517,
        "ps": "159",
        "winner": "est"
    },
    {
        "centroid": [
            74.27932294510711,
            31.502487354825
        ],
        "value": 877,
        "advantage": 0,
        "ps": "160",
        "winner": "pti"
    },
    {
        "centroid": [
            74.28637752144786,
            31.512747003009004
        ],
        "value": 597,
        "advantage": 0,
        "ps": "161",
        "winner": "pti"
    },
    {
        "centroid": [
            74.29038569479671,
            31.509303474246774
        ],
        "value": 447,
        "advantage": 0,
        "ps": "167",
        "winner": "pti"
    },
    {
        "centroid": [
            74.3194053856639,
            31.52308422737943
        ],
        "value": 684,
        "advantage": 0,
        "ps": "173",
        "winner": "pti"
    },
    {
        "centroid": [
            74.35469353013627,
            31.48146815210179
        ],
        "value": 1172,
        "advantage": 600,
        "ps": "175",
        "winner": "est"
    },
    {
        "centroid": [
            74.33046540242371,
            31.548105082910663
        ],
        "value": 1142,
        "advantage": 700,
        "ps": "176",
        "winner": "est"
    },
    {
        "centroid": [
            74.35454814250477,
            31.510126550624435
        ],
        "value": 1006,
        "advantage": 729,
        "ps": "179",
        "winner": "est"
    },
    {
        "centroid": [
            74.32852445561598,
            31.497698504251606
        ],
        "value": 821,
        "advantage": 0,
        "ps": "181",
        "winner": "pti"
    },
    {
        "centroid": [
            74.31378718566032,
            31.536196534600048
        ],
        "value": 886,
        "advantage": 0,
        "ps": "183",
        "winner": "pti"
    },
    {
        "centroid": [
            74.30519298956499,
            31.52682337396273
        ],
        "value": 910,
        "advantage": 59,
        "ps": "185",
        "winner": "pti"
    },
    {
        "centroid": [
            74.31087316344093,
            31.487070000290153
        ],
        "value": 478,
        "advantage": 0,
        "ps": "187",
        "winner": "pti"
    },
    {
        "centroid": [
            74.32235430546847,
            31.5417792377761
        ],
        "value": 451,
        "advantage": 0,
        "ps": "188",
        "winner": "pti"
    },
    {
        "centroid": [
            74.31948539636889,
            31.530260385220203
        ],
        "value": 761,
        "advantage": 0,
        "ps": "189",
        "winner": "pti"
    },
    {
        "centroid": [
            74.31909675951168,
            31.474439903993066
        ],
        "value": 623,
        "advantage": 0,
        "ps": "190",
        "winner": "pti"
    },
    {
        "centroid": [
            74.30930965328115,
            31.52014990730234
        ],
        "value": 1965,
        "advantage": 0,
        "ps": "192",
        "winner": "est"
    },
    {
        "centroid": [
            74.37044945178559,
            31.497678548278515
        ],
        "value": 593,
        "advantage": 0,
        "ps": "194",
        "winner": "pti"
    },
    {
        "centroid": [
            74.30303110677815,
            31.49560193631674
        ],
        "value": 749,
        "advantage": 0,
        "ps": "196",
        "winner": "pti"
    },
    {
        "centroid": [
            74.31838562857682,
            31.5023402225423
        ],
        "value": 1494,
        "advantage": 800,
        "ps": "197",
        "winner": "est"
    },
    {
        "centroid": [
            74.32466358451427,
            31.527614167202685
        ],
        "value": 671,
        "advantage": 300,
        "ps": "199",
        "winner": "est"
    },
    {
        "centroid": [
            74.31064991719745,
            31.533557129898654
        ],
        "value": 1142,
        "advantage": 600,
        "ps": "205",
        "winner": "est"
    },
    {
        "centroid": [
            74.2856382416348,
            31.502809987335198
        ],
        "value": 729,
        "advantage": 0,
        "ps": "207",
        "winner": "pti"
    },
    {
        "centroid": [
            74.29771202520513,
            31.493687187416878
        ],
        "value": 513,
        "advantage": 0,
        "ps": "208",
        "winner": "pti"
    },
    {
        "centroid": [
            74.30517779378047,
            31.478144568784053
        ],
        "value": 1662,
        "advantage": 1000,
        "ps": "209",
        "winner": "est"
    },
    {
        "centroid": [
            74.29619034825615,
            31.51258165005069
        ],
        "value": 745,
        "advantage": -45,
        "ps": "212",
        "winner": "pti"
    },
    {
        "centroid": [
            74.35034375557048,
            31.521727820632357
        ],
        "value": 726,
        "advantage": 400,
        "ps": "213",
        "winner": "est"
    },
    {
        "centroid": [
            74.30443843553134,
            31.516777492622527
        ],
        "value": 654,
        "advantage": 0,
        "ps": "214",
        "winner": "pti"
    },
    {
        "centroid": [
            74.31003946992186,
            31.49399918863017
        ],
        "value": 828,
        "advantage": 0,
        "ps": "216",
        "winner": "pti"
    },
    {
        "centroid": [
            74.33968420035306,
            31.48510211306411
        ],
        "value": 1598,
        "advantage": 0,
        "ps": "217",
        "winner": "est"
    },
    {
        "centroid": [
            74.3496327817905,
            31.531892595603672
        ],
        "value": 1547,
        "advantage": 1000,
        "ps": "218",
        "winner": "est"
    },
    {
        "centroid": [
            74.3444820141501,
            31.536075876144103
        ],
        "value": 642,
        "advantage": 0,
        "ps": "219",
        "winner": "pti"
    },
    {
        "centroid": [
            74.34547573411905,
            31.54407810356445
        ],
        "value": 455,
        "advantage": 0,
        "ps": "220",
        "winner": "pti"
    },
    {
        "centroid": [
            74.34633449370183,
            31.53258214520717
        ],
        "value": 1151,
        "advantage": 1093,
        "ps": "221",
        "winner": "est"
    },
    {
        "centroid": [
            74.28194108524139,
            31.5108549882558
        ],
        "value": 507,
        "advantage": 0,
        "ps": "223",
        "winner": "pti"
    },
    {
        "centroid": [
            74.31179328935274,
            31.500474319650692
        ],
        "value": 1426,
        "advantage": 800,
        "ps": "224",
        "winner": "est"
    },
    {
        "centroid": [
            74.3264229569171,
            31.487620422105504
        ],
        "value": 748,
        "advantage": 400,
        "ps": "225",
        "winner": "est"
    },
    {
        "centroid": [
            74.3115345414094,
            31.474744300064355
        ],
        "value": 819,
        "advantage": 500,
        "ps": "226",
        "winner": "est"
    },
    {
        "centroid": [
            74.34591229384283,
            31.47386020574984
        ],
        "value": 1467,
        "advantage": 873,
        "ps": "228",
        "winner": "est"
    },
    {
        "centroid": [
            74.34680961301468,
            31.48132638431603
        ],
        "value": 842,
        "advantage": 0,
        "ps": "229",
        "winner": "pti"
    },
    {
        "centroid": [
            74.30877950830575,
            31.481731666487367
        ],
        "value": 1160,
        "advantage": 690,
        "ps": "232",
        "winner": "est"
    },
    {
        "centroid": [
            74.35875463702922,
            31.523347455800955
        ],
        "value": 422,
        "advantage": 0,
        "ps": "233",
        "winner": "pti"
    },
    {
        "centroid": [
            74.29885698564115,
            31.515753659492983
        ],
        "value": 559,
        "advantage": 0,
        "ps": "234",
        "winner": "pti"
    },
    {
        "centroid": [
            74.35659669394714,
            31.489676649205787
        ],
        "value": 1707,
        "advantage": 1000,
        "ps": "236",
        "winner": "est"
    },
    {
        "centroid": [
            74.32531197823238,
            31.519012621428065
        ],
        "value": 1258,
        "advantage": 0,
        "ps": "237",
        "winner": "pti"
    },
    {
        "centroid": [
            74.34295259533887,
            31.490152091488227
        ],
        "value": 636,
        "advantage": 0,
        "ps": "244",
        "winner": "pti"
    },
    {
        "centroid": [
            74.30654536986125,
            31.473939536564426
        ],
        "value": 846,
        "advantage": 0,
        "ps": "247",
        "winner": "pti"
    },
    {
        "centroid": [
            74.33911780398542,
            31.503826273680676
        ],
        "value": 735,
        "advantage": 0,
        "ps": "248",
        "winner": "pti"
    },
    {
        "centroid": [
            74.35550789192281,
            31.52744224966489
        ],
        "value": 1118,
        "advantage": 600,
        "ps": "250",
        "winner": "est"
    },
    {
        "centroid": [
            74.30536502668834,
            31.53544224919151
        ],
        "value": 1136,
        "advantage": 700,
        "ps": "251",
        "winner": "est"
    },
    {
        "centroid": [
            74.35916774434565,
            31.502002034282494
        ],
        "value": 496,
        "advantage": 0,
        "ps": "253",
        "winner": "pti"
    },
    {
        "centroid": [
            74.32020990949943,
            31.53528787618681
        ],
        "value": 1034,
        "advantage": 600,
        "ps": "254",
        "winner": "est"
    },
    {
        "centroid": [
            74.31062513638192,
            31.525202397247206
        ],
        "value": 1015,
        "advantage": 0,
        "ps": "255",
        "winner": "pti"
    },
    {
        "centroid": [
            74.36230805475398,
            31.487788748014776
        ],
        "value": 1708,
        "advantage": 1000,
        "ps": "256",
        "winner": "est"
    },
    {
        "centroid": [
            74.33170108339961,
            31.498309329936287
        ],
        "value": 1518,
        "advantage": 600,
        "ps": "257",
        "winner": "est"
    },
    {
        "centroid": [
            74.35915632697382,
            31.49808869512354
        ],
        "value": 1756,
        "advantage": 1000,
        "ps": "258",
        "winner": "est"
    },
    {
        "centroid": [
            74.32865059150679,
            31.494940374726035
        ],
        "value": 679,
        "advantage": 0,
        "ps": "260",
        "winner": "pti"
    },
    {
        "centroid": [
            74.32084752986998,
            31.53838284717003
        ],
        "value": 880,
        "advantage": 0,
        "ps": "263",
        "winner": "pti"
    },
    {
        "centroid": [
            74.32359721046703,
            31.547669247790697
        ],
        "value": 648,
        "advantage": 0,
        "ps": "267",
        "winner": "pti"
    },
    {
        "centroid": [
            74.35584435505963,
            31.52018790471842
        ],
        "value": 1072,
        "advantage": 600,
        "ps": "273",
        "winner": "est"
    },
    {
        "centroid": [
            74.31594584789681,
            31.52047813364434
        ],
        "value": 915,
        "advantage": 0,
        "ps": "274",
        "winner": "pti"
    },
    {
        "centroid": [
            74.30746066788775,
            31.513097472394637
        ],
        "value": 1299,
        "advantage": 600,
        "ps": "275",
        "winner": "est"
    },
    {
        "centroid": [
            74.35423615004525,
            31.50071222978056
        ],
        "value": 883,
        "advantage": 0,
        "ps": "276",
        "winner": "pti"
    },
    {
        "centroid": [
            74.28073635617066,
            31.517393075536702
        ],
        "value": 1614,
        "advantage": 800,
        "ps": "277",
        "winner": "est"
    },
    {
        "centroid": [
            74.34530264524194,
            31.514148389446234
        ],
        "value": 896,
        "advantage": 500,
        "ps": "279",
        "winner": "est"
    },
    {
        "centroid": [
            74.33191343226622,
            31.50149744001822
        ],
        "value": 1005,
        "advantage": 600,
        "ps": "281",
        "winner": "est"
    },
    {
        "centroid": [
            74.33500723197166,
            31.50153381333613
        ],
        "value": 648,
        "advantage": 0,
        "ps": "283",
        "winner": "pti"
    },
    {
        "centroid": [
            74.30942317988917,
            31.53721207328469
        ],
        "value": 1754,
        "advantage": 0,
        "ps": "285",
        "winner": "est"
    },
    {
        "centroid": [
            74.2763723292749,
            31.515610168001615
        ],
        "value": 1656,
        "advantage": 500,
        "ps": "286",
        "winner": "est"
    },
    {
        "centroid": [
            74.32819273015772,
            31.533316837794253
        ],
        "value": 701,
        "advantage": 0,
        "ps": "288",
        "winner": "pti"
    },
    {
        "centroid": [
            74.31521247858011,
            31.525248806412936
        ],
        "value": 1087,
        "advantage": 0,
        "ps": "290",
        "winner": "pti"
    },
    {
        "centroid": [
            74.35581436791784,
            31.507927554966958
        ],
        "value": 985,
        "advantage": 0,
        "ps": "292",
        "winner": "pti"
    },
    {
        "centroid": [
            74.27477028699096,
            31.50700645826302
        ],
        "value": 897,
        "advantage": 0,
        "ps": "296",
        "winner": "pti"
    },
    {
        "centroid": [
            74.33545136005786,
            31.52590320034589
        ],
        "value": 825,
        "advantage": 0,
        "ps": "299",
        "winner": "pti"
    },
    {
        "centroid": [
            74.30516240052557,
            31.521248594767904
        ],
        "value": 881,
        "advantage": 0,
        "ps": "300",
        "winner": "pti"
    },
    {
        "centroid": [
            74.3037332174111,
            31.501453334817832
        ],
        "value": 395,
        "advantage": 0,
        "ps": "303",
        "winner": "pti"
    },
    {
        "centroid": [
            74.3470357461281,
            31.519821856026375
        ],
        "value": 1240,
        "advantage": 800,
        "ps": "306",
        "winner": "est"
    },
    {
        "centroid": [
            74.29727320211006,
            31.52258994756871
        ],
        "value": 563,
        "advantage": 0,
        "ps": "308",
        "winner": "pti"
    },
    {
        "centroid": [
            74.31411350456743,
            31.549242116677522
        ],
        "value": 394,
        "advantage": 0,
        "ps": "311",
        "winner": "pti"
    },
    {
        "centroid": [
            74.34527324936653,
            31.524152755708297
        ],
        "value": 695,
        "advantage": 0,
        "ps": "312",
        "winner": "pti"
    },
    {
        "centroid": [
            74.35261345234548,
            31.52162011467386
        ],
        "value": 651,
        "advantage": 0,
        "ps": "313",
        "winner": "pti"
    },
    {
        "centroid": [
            74.30896877112251,
            31.516221773918843
        ],
        "value": 1244,
        "advantage": 800,
        "ps": "314",
        "winner": "est"
    },
    {
        "centroid": [
            74.30238744989954,
            31.5148449946473
        ],
        "value": 978,
        "advantage": 500,
        "ps": "315",
        "winner": "est"
    },
    {
        "centroid": [
            74.29429782449263,
            31.500720919239694
        ],
        "value": 762,
        "advantage": 400,
        "ps": "316",
        "winner": "est"
    },
    {
        "centroid": [
            74.30701229565403,
            31.518089206417798
        ],
        "value": 432,
        "advantage": 0,
        "ps": "320",
        "winner": "pti"
    },
    {
        "centroid": [
            74.31650913456117,
            31.5404469865273
        ],
        "value": 1947,
        "advantage": 1000,
        "ps": "322",
        "winner": "est"
    },
    {
        "centroid": [
            74.33131475746231,
            31.535645811842283
        ],
        "value": 1716,
        "advantage": 1000,
        "ps": "323",
        "winner": "est"
    },
    {
        "centroid": [
            74.33039164549557,
            31.505287682019215
        ],
        "value": 1714,
        "advantage": 1000,
        "ps": "326",
        "winner": "est"
    },
    {
        "centroid": [
            74.35606023590853,
            31.54858897058641
        ],
        "value": 536,
        "advantage": 0,
        "ps": "327",
        "winner": "pti"
    },
    {
        "centroid": [
            74.3277707282938,
            31.554285901871896
        ],
        "value": 640,
        "advantage": 0,
        "ps": "331",
        "winner": "pti"
    },
    {
        "centroid": [
            74.33891771601088,
            31.528457797022433
        ],
        "value": 695,
        "advantage": 0,
        "ps": "333",
        "winner": "pti"
    },
    {
        "centroid": [
            74.31473069919652,
            31.473374971842095
        ],
        "value": 1324,
        "advantage": 600,
        "ps": "334",
        "winner": "est"
    },
    {
        "centroid": [
            74.31364954977741,
            31.505102735614475
        ],
        "value": 542,
        "advantage": 0,
        "ps": "338",
        "winner": "pti"
    },
    {
        "centroid": [
            74.34708862267125,
            31.486861433743098
        ],
        "value": 1349,
        "advantage": 800,
        "ps": "340",
        "winner": "est"
    },
    {
        "centroid": [
            74.33748174381958,
            31.490035859489222
        ],
        "value": 1114,
        "advantage": 700,
        "ps": "341",
        "winner": "est"
    },
    {
        "centroid": [
            74.2973886521791,
            31.49203931310434
        ],
        "value": 510,
        "advantage": 0,
        "ps": "342",
        "winner": "pti"
    },
    {
        "centroid": [
            74.33980618909406,
            31.521251940975777
        ],
        "value": 428,
        "advantage": 0,
        "ps": "343",
        "winner": "pti"
    },
    {
        "centroid": [
            74.34866658785663,
            31.491824593034842
        ],
        "value": 746,
        "advantage": 0,
        "ps": "344",
        "winner": "pti"
    },
    {
        "centroid": [
            74.36257909857028,
            31.49893627644146
        ],
        "value": 1396,
        "advantage": 800,
        "ps": "345",
        "winner": "est"
    },
    {
        "centroid": [
            74.35460067712931,
            31.535794871051973
        ],
        "value": 895,
        "advantage": 0,
        "ps": "346",
        "winner": "pti"
    },
    {
        "centroid": [
            74.30069775464591,
            31.48345721632564
        ],
        "value": 525,
        "advantage": 0,
        "ps": "347",
        "winner": "pti"
    },
    {
        "centroid": [
            74.34243449792962,
            31.53289470806566
        ],
        "value": 626,
        "advantage": 0,
        "ps": "348",
        "winner": "est"
    },
    {
        "centroid": [
            74.34213370743274,
            31.527402478378264
        ],
        "value": 989,
        "advantage": 600,
        "ps": "349",
        "winner": "est"
    },
    {
        "centroid": [
            74.33030814836535,
            31.4927039370952
        ],
        "value": 1975,
        "advantage": 600,
        "ps": "351",
        "winner": "est"
    },
    {
        "centroid": [
            74.30287119511861,
            31.51050970439744
        ],
        "value": 1666,
        "advantage": 938,
        "ps": "357",
        "winner": "est"
    },
    {
        "centroid": [
            74.3033419478701,
            31.530616126757963
        ],
        "value": 620,
        "advantage": 0,
        "ps": "358",
        "winner": "pti"
    },
    {
        "centroid": [
            74.32625098929627,
            31.51061618134176
        ],
        "value": 382,
        "advantage": 0,
        "ps": "361",
        "winner": "pti"
    },
    {
        "centroid": [
            74.32051124741494,
            31.553742142725074
        ],
        "value": 464,
        "advantage": 0,
        "ps": "364",
        "winner": "pti"
    },
    {
        "centroid": [
            74.31693986603013,
            31.54721186445197
        ],
        "value": 770,
        "advantage": 0,
        "ps": "366",
        "winner": "pti"
    },
    {
        "centroid": [
            74.33628820813367,
            31.495396919715056
        ],
        "value": 466,
        "advantage": 0,
        "ps": "367",
        "winner": "pti"
    },
    {
        "centroid": [
            74.30654137796506,
            31.498618837179293
        ],
        "value": 1250,
        "advantage": 0,
        "ps": "372",
        "winner": "est"
    },
    {
        "centroid": [
            74.33227870203497,
            31.4903217963034
        ],
        "value": 411,
        "advantage": 0,
        "ps": "375",
        "winner": "pti"
    },
    {
        "centroid": [
            74.30897972496466,
            31.53109465234517
        ],
        "value": 479,
        "advantage": 0,
        "ps": "378",
        "winner": "pti"
    },
    {
        "centroid": [
            74.35430128437743,
            31.512335309952466
        ],
        "value": 923,
        "advantage": -81,
        "ps": "379",
        "winner": "pti"
    },
    {
        "centroid": [
            74.31500555679028,
            31.51415755051565
        ],
        "value": 555,
        "advantage": 0,
        "ps": "381",
        "winner": "pti"
    },
    {
        "centroid": [
            74.3480548084397,
            31.537738446874755
        ],
        "value": 392,
        "advantage": 0,
        "ps": "383",
        "winner": "pti"
    },
    {
        "centroid": [
            74.29121460730842,
            31.503838423866195
        ],
        "value": 353,
        "advantage": 0,
        "ps": "386",
        "winner": "pti"
    },
    {
        "centroid": [
            74.35234936944134,
            31.49124320226271
        ],
        "value": 1091,
        "advantage": 700,
        "ps": "388",
        "winner": "est"
    },
    {
        "centroid": [
            74.3662375655376,
            31.487864952660697
        ],
        "value": 635,
        "advantage": 300,
        "ps": "389",
        "winner": "est"
    },
    {
        "centroid": [
            74.32442552914176,
            31.55260599724342
        ],
        "value": 347,
        "advantage": 400,
        "ps": "391",
        "winner": "est"
    },
    {
        "centroid": [
            74.29668458665343,
            31.488213523459915
        ],
        "value": 392,
        "advantage": 0,
        "ps": "393",
        "winner": "pti"
    },
    {
        "centroid": [
            74.31506236704872,
            31.53266118543911
        ],
        "value": 1757,
        "advantage": 600,
        "ps": "394",
        "winner": "est"
    },
    {
        "centroid": [
            74.29324962758339,
            31.49418129316407
        ],
        "value": 940,
        "advantage": 0,
        "ps": "396",
        "winner": "pti"
    },
    {
        "centroid": [
            74.3337212661854,
            31.552116745749615
        ],
        "value": 1310,
        "advantage": 600,
        "ps": "397",
        "winner": "est"
    },
    {
        "centroid": [
            74.33627138164903,
            31.53097543830878
        ],
        "value": 936,
        "advantage": 0,
        "ps": "398",
        "winner": "pti"
    },
    {
        "centroid": [
            74.35016163229217,
            31.540149919921127
        ],
        "value": 1628,
        "advantage": 1000,
        "ps": "399",
        "winner": "est"
    },
    {
        "centroid": [
            74.3490307803498,
            31.552000821452065
        ],
        "value": 1802,
        "advantage": 1568,
        "ps": "401",
        "winner": "est"
    },
    {
        "centroid": [
            74.32795284167776,
            31.540121871546564
        ],
        "value": 653,
        "advantage": 12,
        "ps": "402",
        "winner": "pti"
    },
    {
        "centroid": [
            74.30988064956328,
            31.50739328869283
        ],
        "value": 994,
        "advantage": 0,
        "ps": "405",
        "winner": "pti"
    },
    {
        "centroid": [
            74.34312824853419,
            31.51209345322317
        ],
        "value": 665,
        "advantage": 0,
        "ps": "406",
        "winner": "pti"
    },
    {
        "centroid": [
            74.32500373764954,
            31.502098635608498
        ],
        "value": 593,
        "advantage": 100,
        "ps": "407",
        "winner": "est"
    },
    {
        "centroid": [
            74.32435518113928,
            31.53570659917818
        ],
        "value": 652,
        "advantage": 0,
        "ps": "410",
        "winner": "pti"
    },
    {
        "centroid": [
            74.35154207083927,
            31.549863136763623
        ],
        "value": 1005,
        "advantage": 0,
        "ps": "412",
        "winner": "pti"
    },
    {
        "centroid": [
            74.28792304346179,
            31.515699202456847
        ],
        "value": 741,
        "advantage": 0,
        "ps": "414",
        "winner": "pti"
    },
    {
        "centroid": [
            74.29797660927633,
            31.51838993822883
        ],
        "value": 685,
        "advantage": -116,
        "ps": "417",
        "winner": "pti"
    },
    {
        "centroid": [
            74.30139889934564,
            31.507193039668675
        ],
        "value": 558,
        "advantage": 0,
        "ps": "419",
        "winner": "pti"
    },
    {
        "centroid": [
            74.33341281712015,
            31.517630598022635
        ],
        "value": 1306,
        "advantage": 600,
        "ps": "423",
        "winner": "est"
    },
    {
        "centroid": [
            74.35194729059887,
            31.488387513970473
        ],
        "value": 604,
        "advantage": 0,
        "ps": "427",
        "winner": "pti"
    },
    {
        "centroid": [
            74.35438753676951,
            31.524396883692383
        ],
        "value": 676,
        "advantage": 0,
        "ps": "429",
        "winner": "pti"
    },
    {
        "centroid": [
            74.31424473124478,
            31.56822858289997
        ],
        "value": 1931,
        "advantage": 1000,
        "ps": "1",
        "winner": "est"
    },
    {
        "centroid": [
            74.25908170778627,
            31.555817797401403
        ],
        "value": 752,
        "advantage": 0,
        "ps": "2",
        "winner": "pti"
    },
    {
        "centroid": [
            74.32210761092469,
            31.56353816341994
        ],
        "value": 778,
        "advantage": 0,
        "ps": "5",
        "winner": "pti"
    },
    {
        "centroid": [
            74.28387706754783,
            31.59433459996096
        ],
        "value": 1728,
        "advantage": 1000,
        "ps": "6",
        "winner": "est"
    },
    {
        "centroid": [
            74.25762318402623,
            31.56349144709889
        ],
        "value": 525,
        "advantage": 0,
        "ps": "7",
        "winner": "pti"
    },
    {
        "centroid": [
            74.29698455015796,
            31.560253391807002
        ],
        "value": 545,
        "advantage": -10,
        "ps": "8",
        "winner": "pti"
    },
    {
        "centroid": [
            74.30945825065815,
            31.567322320369158
        ],
        "value": 676,
        "advantage": 0,
        "ps": "20",
        "winner": "pti"
    },
    {
        "centroid": [
            74.30480847425179,
            31.58602300890534
        ],
        "value": 432,
        "advantage": 0,
        "ps": "23",
        "winner": "pti"
    },
    {
        "centroid": [
            74.30986804948292,
            31.569721223244805
        ],
        "value": 1290,
        "advantage": 1134,
        "ps": "24",
        "winner": "est"
    },
    {
        "centroid": [
            74.30234605418785,
            31.56343440511596
        ],
        "value": 586,
        "advantage": 0,
        "ps": "27",
        "winner": "pti"
    },
    {
        "centroid": [
            74.28523926382434,
            31.60121806118661
        ],
        "value": 348,
        "advantage": 100,
        "ps": "28",
        "winner": "est"
    },
    {
        "centroid": [
            74.27437831804185,
            31.593587995440902
        ],
        "value": 424,
        "advantage": 0,
        "ps": "32",
        "winner": "pti"
    },
    {
        "centroid": [
            74.28979547415274,
            31.584466080987642
        ],
        "value": 490,
        "advantage": 0,
        "ps": "34",
        "winner": "pti"
    },
    {
        "centroid": [
            74.2629869751323,
            31.552883050580558
        ],
        "value": 1876,
        "advantage": 1000,
        "ps": "35",
        "winner": "est"
    },
    {
        "centroid": [
            74.26664067657585,
            31.583162208184422
        ],
        "value": 587,
        "advantage": 0,
        "ps": "36",
        "winner": "pti"
    },
    {
        "centroid": [
            74.30348595066151,
            31.589278661369775
        ],
        "value": 2091,
        "advantage": 1000,
        "ps": "37",
        "winner": "est"
    },
    {
        "centroid": [
            74.28752273313324,
            31.59713926992497
        ],
        "value": 693,
        "advantage": 0,
        "ps": "38",
        "winner": "pti"
    },
    {
        "centroid": [
            74.29367196791742,
            31.58996761634128
        ],
        "value": 421,
        "advantage": 0,
        "ps": "39",
        "winner": "pti"
    },
    {
        "centroid": [
            74.31793194566426,
            31.55699517541646
        ],
        "value": 367,
        "advantage": 0,
        "ps": "41",
        "winner": "pti"
    },
    {
        "centroid": [
            74.31120579304655,
            31.567367975818293
        ],
        "value": 826,
        "advantage": 0,
        "ps": "47",
        "winner": "est"
    },
    {
        "centroid": [
            74.30181913316152,
            31.594838426863646
        ],
        "value": 554,
        "advantage": 0,
        "ps": "50",
        "winner": "est"
    },
    {
        "centroid": [
            74.29350054559254,
            31.598369993877224
        ],
        "value": 742,
        "advantage": 0,
        "ps": "62",
        "winner": "pti"
    },
    {
        "centroid": [
            74.25017677476549,
            31.55309811606302
        ],
        "value": 2060,
        "advantage": 1000,
        "ps": "63",
        "winner": "est"
    },
    {
        "centroid": [
            74.26103481632903,
            31.56003725380928
        ],
        "value": 2137,
        "advantage": 1000,
        "ps": "65",
        "winner": "est"
    },
    {
        "centroid": [
            74.28806056926982,
            31.57811969507997
        ],
        "value": 709,
        "advantage": 0,
        "ps": "68",
        "winner": "pti"
    },
    {
        "centroid": [
            74.30789861529844,
            31.576938241785484
        ],
        "value": 19,
        "advantage": 0,
        "ps": "69",
        "winner": "pti"
    },
    {
        "centroid": [
            74.26364300671614,
            31.564605978219895
        ],
        "value": 570,
        "advantage": 0,
        "ps": "70",
        "winner": "pti"
    },
    {
        "centroid": [
            74.2851482888922,
            31.55388589115654
        ],
        "value": 768,
        "advantage": 0,
        "ps": "71",
        "winner": "pti"
    },
    {
        "centroid": [
            74.2889731118775,
            31.604585275844432
        ],
        "value": 632,
        "advantage": 0,
        "ps": "75",
        "winner": "pti"
    },
    {
        "centroid": [
            74.25766851668615,
            31.567750637967865
        ],
        "value": 630,
        "advantage": 0,
        "ps": "76",
        "winner": "pti"
    },
    {
        "centroid": [
            74.28479333533677,
            31.567271147744467
        ],
        "value": 1241,
        "advantage": 500,
        "ps": "77",
        "winner": "est"
    },
    {
        "centroid": [
            74.30850429065315,
            31.55902711190953
        ],
        "value": 335,
        "advantage": 0,
        "ps": "78",
        "winner": "pti"
    },
    {
        "centroid": [
            74.28331650496794,
            31.585596568120582
        ],
        "value": 511,
        "advantage": 0,
        "ps": "80",
        "winner": "pti"
    },
    {
        "centroid": [
            74.3013140196616,
            31.559130582859623
        ],
        "value": 717,
        "advantage": 0,
        "ps": "82",
        "winner": "est"
    },
    {
        "centroid": [
            74.27918629219783,
            31.59408467895886
        ],
        "value": 398,
        "advantage": 0,
        "ps": "83",
        "winner": "est"
    },
    {
        "centroid": [
            74.33409339721617,
            31.558027548768127
        ],
        "value": 1771,
        "advantage": 1000,
        "ps": "84",
        "winner": "est"
    },
    {
        "centroid": [
            74.272410438922,
            31.576569285241458
        ],
        "value": 697,
        "advantage": 0,
        "ps": "87",
        "winner": "pti"
    },
    {
        "centroid": [
            74.31639838544194,
            31.578064253339363
        ],
        "value": 1794,
        "advantage": 1000,
        "ps": "89",
        "winner": "est"
    },
    {
        "centroid": [
            74.25287525123738,
            31.559797797314083
        ],
        "value": 440,
        "advantage": 0,
        "ps": "90",
        "winner": "pti"
    },
    {
        "centroid": [
            74.30428790964564,
            31.598778970228736
        ],
        "value": 2019,
        "advantage": 1749,
        "ps": "91",
        "winner": "est"
    },
    {
        "centroid": [
            74.30278042023866,
            31.580645311314427
        ],
        "value": 645,
        "advantage": 0,
        "ps": "92",
        "winner": "est"
    },
    {
        "centroid": [
            74.30834588651629,
            31.56080889647426
        ],
        "value": 724,
        "advantage": 0,
        "ps": "94",
        "winner": "est"
    },
    {
        "centroid": [
            74.27011697010445,
            31.570384086023665
        ],
        "value": 628,
        "advantage": 0,
        "ps": "97",
        "winner": "est"
    },
    {
        "centroid": [
            74.31846918639663,
            31.575890537878756
        ],
        "value": 440,
        "advantage": 0,
        "ps": "100",
        "winner": "est"
    },
    {
        "centroid": [
            74.31101866841627,
            31.555799205869086
        ],
        "value": 508,
        "advantage": 0,
        "ps": "101",
        "winner": "pti"
    },
    {
        "centroid": [
            74.30111288959637,
            31.600625347488673
        ],
        "value": 466,
        "advantage": 0,
        "ps": "102",
        "winner": "pti"
    },
    {
        "centroid": [
            74.29774626092028,
            31.59534374174636
        ],
        "value": 320,
        "advantage": 0,
        "ps": "103",
        "winner": "pti"
    },
    {
        "centroid": [
            74.2753533223439,
            31.567805753583695
        ],
        "value": 1040,
        "advantage": 0,
        "ps": "107",
        "winner": "pti"
    },
    {
        "centroid": [
            74.29465160491556,
            31.603399717722972
        ],
        "value": 1916,
        "advantage": 1000,
        "ps": "109",
        "winner": "est"
    },
    {
        "centroid": [
            74.29949155514555,
            31.59027562357698
        ],
        "value": 1589,
        "advantage": 1231,
        "ps": "110",
        "winner": "est"
    },
    {
        "centroid": [
            74.27125622784104,
            31.588955461612713
        ],
        "value": 1969,
        "advantage": 1000,
        "ps": "113",
        "winner": "est"
    },
    {
        "centroid": [
            74.26473360227662,
            31.574145225564767
        ],
        "value": 2092,
        "advantage": 1000,
        "ps": "116",
        "winner": "est"
    },
    {
        "centroid": [
            74.29023077345212,
            31.5917057195472
        ],
        "value": 789,
        "advantage": 0,
        "ps": "117",
        "winner": "pti"
    },
    {
        "centroid": [
            74.30340540982573,
            31.566549342875003
        ],
        "value": 825,
        "advantage": 0,
        "ps": "118",
        "winner": "pti"
    },
    {
        "centroid": [
            74.29483671972774,
            31.579466002408747
        ],
        "value": 845,
        "advantage": 0,
        "ps": "120",
        "winner": "pti"
    },
    {
        "centroid": [
            74.27485807507716,
            31.576212252149247
        ],
        "value": 543,
        "advantage": 165,
        "ps": "121",
        "winner": "est"
    },
    {
        "centroid": [
            74.32045252193795,
            31.574230987867697
        ],
        "value": 1505,
        "advantage": 0,
        "ps": "122",
        "winner": "est"
    },
    {
        "centroid": [
            74.28292651799103,
            31.581018903281755
        ],
        "value": 654,
        "advantage": 0,
        "ps": "124",
        "winner": "pti"
    },
    {
        "centroid": [
            74.31278517861351,
            31.557849340301107
        ],
        "value": 387,
        "advantage": 0,
        "ps": "126",
        "winner": "pti"
    },
    {
        "centroid": [
            74.30820626224235,
            31.566287922689117
        ],
        "value": 581,
        "advantage": 0,
        "ps": "127",
        "winner": "pti"
    },
    {
        "centroid": [
            74.30304326349624,
            31.57438708688535
        ],
        "value": 665,
        "advantage": 0,
        "ps": "130",
        "winner": "pti"
    },
    {
        "centroid": [
            74.30449122209963,
            31.593562604858136
        ],
        "value": 374,
        "advantage": 0,
        "ps": "139",
        "winner": "pti"
    },
    {
        "centroid": [
            74.29195468331189,
            31.56655857290616
        ],
        "value": 1363,
        "advantage": 700,
        "ps": "140",
        "winner": "est"
    },
    {
        "centroid": [
            74.2936869082301,
            31.559098073127288
        ],
        "value": 770,
        "advantage": 385,
        "ps": "142",
        "winner": "est"
    },
    {
        "centroid": [
            74.24964920111185,
            31.556727123081426
        ],
        "value": 551,
        "advantage": 0,
        "ps": "143",
        "winner": "est"
    },
    {
        "centroid": [
            74.29023983299005,
            31.571510563712668
        ],
        "value": 412,
        "advantage": 0,
        "ps": "144",
        "winner": "est"
    },
    {
        "centroid": [
            74.26594790257587,
            31.578360869005802
        ],
        "value": 791,
        "advantage": 61,
        "ps": "146",
        "winner": "pti"
    },
    {
        "centroid": [
            74.25817423505876,
            31.552056952263616
        ],
        "value": 520,
        "advantage": 0,
        "ps": "147",
        "winner": "pti"
    },
    {
        "centroid": [
            74.29095572298671,
            31.574471276301225
        ],
        "value": 571,
        "advantage": 0,
        "ps": "149",
        "winner": "pti"
    },
    {
        "centroid": [
            74.2814753457648,
            31.567502255927156
        ],
        "value": 508,
        "advantage": 0,
        "ps": "150",
        "winner": "pti"
    },
    {
        "centroid": [
            74.2514170317358,
            31.565298835804747
        ],
        "value": 594,
        "advantage": 0,
        "ps": "155",
        "winner": "pti"
    },
    {
        "centroid": [
            74.28150742405128,
            31.577390098251428
        ],
        "value": 561,
        "advantage": 0,
        "ps": "158",
        "winner": "pti"
    },
    {
        "centroid": [
            74.3061682753462,
            31.55562179561561
        ],
        "value": 697,
        "advantage": 0,
        "ps": "162",
        "winner": "pti"
    },
    {
        "centroid": [
            74.30988124091179,
            31.564982617182505
        ],
        "value": 693,
        "advantage": 0,
        "ps": "165",
        "winner": "pti"
    },
    {
        "centroid": [
            74.30589669057458,
            31.56445074289682
        ],
        "value": 583,
        "advantage": 0,
        "ps": "166",
        "winner": "pti"
    },
    {
        "centroid": [
            74.2685975726252,
            31.573794893857617
        ],
        "value": 517,
        "advantage": 0,
        "ps": "167",
        "winner": "pti"
    },
    {
        "centroid": [
            74.28044156094455,
            31.591157537626557
        ],
        "value": 1023,
        "advantage": 0,
        "ps": "169",
        "winner": "est"
    },
    {
        "centroid": [
            74.27088981501626,
            31.57867965185578
        ],
        "value": 1541,
        "advantage": 0,
        "ps": "170",
        "winner": "est"
    },
    {
        "centroid": [
            74.27680262619108,
            31.553564434151717
        ],
        "value": 478,
        "advantage": 0,
        "ps": "171",
        "winner": "pti"
    },
    {
        "centroid": [
            74.28210465285787,
            31.597652419685517
        ],
        "value": 302,
        "advantage": 0,
        "ps": "172",
        "winner": "pti"
    },
    {
        "centroid": [
            74.29086978038649,
            31.561898330012593
        ],
        "value": 379,
        "advantage": 0,
        "ps": "175",
        "winner": "pti"
    },
    {
        "centroid": [
            74.29769542046805,
            31.56149892762397
        ],
        "value": 663,
        "advantage": 0,
        "ps": "176",
        "winner": "pti"
    },
    {
        "centroid": [
            74.29158814684243,
            31.59518825645225
        ],
        "value": 463,
        "advantage": 0,
        "ps": "177",
        "winner": "pti"
    },
    {
        "centroid": [
            74.27146609513717,
            31.559444155562467
        ],
        "value": 524,
        "advantage": 0,
        "ps": "178",
        "winner": "pti"
    },
    {
        "centroid": [
            74.27928132488361,
            31.58207501476163
        ],
        "value": 363,
        "advantage": 0,
        "ps": "179",
        "winner": "pti"
    },
    {
        "centroid": [
            74.28835401473891,
            31.581997049537883
        ],
        "value": 884,
        "advantage": 0,
        "ps": "182",
        "winner": "pti"
    },
    {
        "centroid": [
            74.27554798470837,
            31.57897462069689
        ],
        "value": 766,
        "advantage": 0,
        "ps": "184",
        "winner": "pti"
    },
    {
        "centroid": [
            74.2951739367324,
            31.564911526535624
        ],
        "value": 778,
        "advantage": 0,
        "ps": "190",
        "winner": "pti"
    },
    {
        "centroid": [
            74.29149308612823,
            31.58255853665366
        ],
        "value": 313,
        "advantage": 0,
        "ps": "192",
        "winner": "pti"
    },
    {
        "centroid": [
            74.2788729492869,
            31.564843977504946
        ],
        "value": 1028,
        "advantage": 0,
        "ps": "194",
        "winner": "pti"
    },
    {
        "centroid": [
            74.30816933455829,
            31.563310637416105
        ],
        "value": 662,
        "advantage": -20,
        "ps": "195",
        "winner": "pti"
    },
    {
        "centroid": [
            74.34067842124345,
            31.556950333456225
        ],
        "value": 1452,
        "advantage": 1271,
        "ps": "202",
        "winner": "est"
    },
    {
        "centroid": [
            74.2980393490379,
            31.58692211469645
        ],
        "value": 276,
        "advantage": 0,
        "ps": "204",
        "winner": "pti"
    },
    {
        "centroid": [
            74.30847946786048,
            31.552490783289155
        ],
        "value": 574,
        "advantage": 0,
        "ps": "206",
        "winner": "pti"
    },
    {
        "centroid": [
            74.31189788338096,
            31.56498258659372
        ],
        "value": 384,
        "advantage": 0,
        "ps": "207",
        "winner": "est"
    },
    {
        "centroid": [
            74.30532003003258,
            31.56146607758434
        ],
        "value": 686,
        "advantage": 0,
        "ps": "209",
        "winner": "est"
    },
    {
        "centroid": [
            74.25395644924137,
            31.55344389825648
        ],
        "value": 371,
        "advantage": 0,
        "ps": "210",
        "winner": "est"
    },
    {
        "centroid": [
            74.27630143329705,
            31.584952862462565
        ],
        "value": 437,
        "advantage": 0,
        "ps": "212",
        "winner": "pti"
    },
    {
        "centroid": [
            74.27346492979632,
            31.55748046143204
        ],
        "value": 680,
        "advantage": 0,
        "ps": "215",
        "winner": "pti"
    },
    {
        "centroid": [
            74.29912427553192,
            31.599741127637838
        ],
        "value": 2081,
        "advantage": 1608,
        "ps": "217",
        "winner": "est"
    },
    {
        "centroid": [
            74.29385369539645,
            31.586889434609475
        ],
        "value": 921,
        "advantage": 0,
        "ps": "219",
        "winner": "pti"
    },
    {
        "centroid": [
            74.26795675139779,
            31.56101679124702
        ],
        "value": 539,
        "advantage": 0,
        "ps": "220",
        "winner": "pti"
    },
    {
        "centroid": [
            74.29228623720675,
            31.60745169578785
        ],
        "value": 440,
        "advantage": 0,
        "ps": "221",
        "winner": "pti"
    },
    {
        "centroid": [
            74.2846855765936,
            31.59065376866267
        ],
        "value": 957,
        "advantage": 0,
        "ps": "222",
        "winner": "pti"
    },
    {
        "centroid": [
            74.28837694644082,
            31.557745260230284
        ],
        "value": 602,
        "advantage": 0,
        "ps": "223",
        "winner": "pti"
    },
    {
        "centroid": [
            74.2553571621937,
            31.5617176127209
        ],
        "value": 725,
        "advantage": 0,
        "ps": "224",
        "winner": "pti"
    },
    {
        "centroid": [
            74.31412697051302,
            31.564114449464228
        ],
        "value": 651,
        "advantage": 18,
        "ps": "225",
        "winner": "pti"
    },
    {
        "centroid": [
            74.2703118789888,
            31.58496580898829
        ],
        "value": 337,
        "advantage": 0,
        "ps": "231",
        "winner": "pti"
    },
    {
        "centroid": [
            74.29420291378806,
            31.552740580559092
        ],
        "value": 317,
        "advantage": 0,
        "ps": "234",
        "winner": "pti"
    },
    {
        "centroid": [
            74.30136267418615,
            31.591771055184687
        ],
        "value": 566,
        "advantage": 0,
        "ps": "236",
        "winner": "pti"
    },
    {
        "centroid": [
            74.29670598493713,
            31.57465337185611
        ],
        "value": 532,
        "advantage": 0,
        "ps": "238",
        "winner": "pti"
    },
    {
        "centroid": [
            74.29756998137955,
            31.592477760482836
        ],
        "value": 662,
        "advantage": 0,
        "ps": "243",
        "winner": "est"
    },
    {
        "centroid": [
            74.3214412926959,
            31.56030274451977
        ],
        "value": 1022,
        "advantage": 0,
        "ps": "245",
        "winner": "pti"
    },
    {
        "centroid": [
            74.26963476315323,
            31.559793035395558
        ],
        "value": 1988,
        "advantage": 1000,
        "ps": "246",
        "winner": "est"
    },
    {
        "centroid": [
            74.2729386366268,
            31.5711061971155
        ],
        "value": 388,
        "advantage": 0,
        "ps": "251",
        "winner": "est"
    },
    {
        "centroid": [
            74.30010508496996,
            31.603183133503514
        ],
        "value": 1717,
        "advantage": 1000,
        "ps": "252",
        "winner": "est"
    },
    {
        "centroid": [
            74.29996506630107,
            31.597113128650214
        ],
        "value": 616,
        "advantage": 0,
        "ps": "256",
        "winner": "est"
    },
    {
        "centroid": [
            74.27765577095882,
            31.57507466338245
        ],
        "value": 932,
        "advantage": 0,
        "ps": "258",
        "winner": "est"
    },
    {
        "centroid": [
            74.28070514461156,
            31.5524568260422
        ],
        "value": 1741,
        "advantage": 1000,
        "ps": "260",
        "winner": "est"
    },
    {
        "centroid": [
            74.3061782304507,
            31.568051052201024
        ],
        "value": 1839,
        "advantage": 1000,
        "ps": "262",
        "winner": "est"
    },
    {
        "centroid": [
            74.29884800717075,
            31.556317733702837
        ],
        "value": 548,
        "advantage": 0,
        "ps": "263",
        "winner": "pti"
    },
    {
        "centroid": [
            74.30583012791386,
            31.558967930351304
        ],
        "value": 443,
        "advantage": 0,
        "ps": "265",
        "winner": "est"
    },
    {
        "centroid": [
            74.3179095248768,
            31.56557217406605
        ],
        "value": 704,
        "advantage": 0,
        "ps": "267",
        "winner": "est"
    },
    {
        "centroid": [
            74.28410945727576,
            31.562852385637648
        ],
        "value": 513,
        "advantage": -170,
        "ps": "269",
        "winner": "pti"
    },
    {
        "centroid": [
            74.28810260429523,
            31.585197902562708
        ],
        "value": 751,
        "advantage": 252,
        "ps": "270",
        "winner": "est"
    },
    {
        "centroid": [
            74.27717891466021,
            31.58097735436171
        ],
        "value": 682,
        "advantage": 0,
        "ps": "271",
        "winner": "est"
    },
    {
        "centroid": [
            74.27139575520123,
            31.56733291461063
        ],
        "value": 353,
        "advantage": 0,
        "ps": "273",
        "winner": "pti"
    },
    {
        "centroid": [
            74.30785382107588,
            31.5726823748447
        ],
        "value": 1087,
        "advantage": 0,
        "ps": "281",
        "winner": "est"
    },
    {
        "centroid": [
            74.25610936655667,
            31.558496626973827
        ],
        "value": 2275,
        "advantage": 1950,
        "ps": "283",
        "winner": "est"
    },
    {
        "centroid": [
            74.29124232023564,
            31.586782664013363
        ],
        "value": 2013,
        "advantage": 1502,
        "ps": "284",
        "winner": "est"
    },
    {
        "centroid": [
            74.27751952843822,
            31.570867975234062
        ],
        "value": 325,
        "advantage": 0,
        "ps": "285",
        "winner": "est"
    },
    {
        "centroid": [
            74.29547972429418,
            31.583488182853984
        ],
        "value": 419,
        "advantage": 0,
        "ps": "286",
        "winner": "est"
    },
    {
        "centroid": [
            74.31402508298152,
            31.55358964648057
        ],
        "value": 1034,
        "advantage": 0,
        "ps": "289",
        "winner": "est"
    },
    {
        "centroid": [
            74.27354098118374,
            31.57721497747507
        ],
        "value": 2541,
        "advantage": 1500,
        "ps": "291",
        "winner": "est"
    },
    {
        "centroid": [
            74.29257203205202,
            31.576301411463533
        ],
        "value": 521,
        "advantage": 0,
        "ps": "292",
        "winner": "est"
    },
    {
        "centroid": [
            74.27501102866836,
            31.563151376065637
        ],
        "value": 935,
        "advantage": 0,
        "ps": "293",
        "winner": "pti"
    },
    {
        "centroid": [
            74.29006356482141,
            31.55235651354722
        ],
        "value": 679,
        "advantage": 0,
        "ps": "294",
        "winner": "est"
    },
    {
        "centroid": [
            74.31442158514392,
            31.560671278986913
        ],
        "value": 1929,
        "advantage": 1000,
        "ps": "296",
        "winner": "est"
    },
    {
        "centroid": [
            74.28554400017985,
            31.58260481488865
        ],
        "value": 1778,
        "advantage": 0,
        "ps": "297",
        "winner": "est"
    },
    {
        "centroid": [
            74.2856953182728,
            31.586822575985668
        ],
        "value": 378,
        "advantage": 0,
        "ps": "298",
        "winner": "est"
    },
    {
        "centroid": [
            74.2804176651985,
            31.557922701669987
        ],
        "value": 2201,
        "advantage": 1911,
        "ps": "300",
        "winner": "est"
    },
    {
        "centroid": [
            74.32714105577843,
            31.557217761946674
        ],
        "value": 2054,
        "advantage": 1000,
        "ps": "302",
        "winner": "est"
    },
    {
        "centroid": [
            74.2711947847161,
            31.563513983831513
        ],
        "value": 1699,
        "advantage": 1000,
        "ps": "303",
        "winner": "est"
    },
    {
        "centroid": [
            74.28701439021484,
            31.567860378616313
        ],
        "value": 1892,
        "advantage": 1000,
        "ps": "304",
        "winner": "est"
    },
    {
        "centroid": [
            74.29161438585636,
            31.59738073000536
        ],
        "value": 632,
        "advantage": 0,
        "ps": "305",
        "winner": "pti"
    },
    {
        "centroid": [
            74.27638418022988,
            31.590991032396964
        ],
        "value": 320,
        "advantage": 0,
        "ps": "306",
        "winner": "pti"
    },
    {
        "centroid": [
            74.2648175489581,
            31.560486583435054
        ],
        "value": 429,
        "advantage": 0,
        "ps": "311",
        "winner": "pti"
    },
    {
        "centroid": [
            74.27376116593085,
            31.58173674290827
        ],
        "value": 360,
        "advantage": 0,
        "ps": "312",
        "winner": "pti"
    },
    {
        "centroid": [
            74.31814756376464,
            31.56230048739472
        ],
        "value": 1923,
        "advantage": 1000,
        "ps": "314",
        "winner": "est"
    },
    {
        "centroid": [
            74.27322204993646,
            31.5746401786629
        ],
        "value": 604,
        "advantage": 0,
        "ps": "316",
        "winner": "est"
    },
    {
        "centroid": [
            74.31423455676105,
            31.573862908120915
        ],
        "value": 1664,
        "advantage": 1279,
        "ps": "318",
        "winner": "est"
    },
    {
        "centroid": [
            74.26757626164927,
            31.564449123382474
        ],
        "value": 715,
        "advantage": 0,
        "ps": "325",
        "winner": "pti"
    },
    {
        "centroid": [
            74.28813024533284,
            31.588799628782674
        ],
        "value": 688,
        "advantage": 0,
        "ps": "326",
        "winner": "est"
    },
    {
        "centroid": [
            74.32669839304886,
            31.56205641573204
        ],
        "value": 478,
        "advantage": 0,
        "ps": "328",
        "winner": "pti"
    },
    {
        "centroid": [
            74.31921986151508,
            31.569021147769313
        ],
        "value": 511,
        "advantage": 0,
        "ps": "332",
        "winner": "pti"
    },
    {
        "centroid": [
            74.28860085204612,
            31.594652788460284
        ],
        "value": 657,
        "advantage": 0,
        "ps": "335",
        "winner": "est"
    },
    {
        "centroid": [
            74.28084508687753,
            31.584853594841885
        ],
        "value": 353,
        "advantage": 0,
        "ps": "337",
        "winner": "est"
    },
    {
        "centroid": [
            74.29376730693902,
            31.610666038295516
        ],
        "value": 378,
        "advantage": 0,
        "ps": "340",
        "winner": "est"
    },
    {
        "centroid": [
            74.28121749370882,
            31.58821952557867
        ],
        "value": 194,
        "advantage": 0,
        "ps": "343",
        "winner": "est"
    },
    {
        "centroid": [
            74.3108728728779,
            31.559909597068145
        ],
        "value": 550,
        "advantage": 0,
        "ps": "345",
        "winner": "est"
    },
    {
        "centroid": [
            74.27928008857228,
            31.586414401122372
        ],
        "value": 394,
        "advantage": 0,
        "ps": "346",
        "winner": "est"
    },
    {
        "centroid": [
            74.26724377301544,
            31.556074323516604
        ],
        "value": 439,
        "advantage": 0,
        "ps": "348",
        "winner": "est"
    },
    {
        "centroid": [
            74.29428928906628,
            31.594849494047526
        ],
        "value": 475,
        "advantage": 0,
        "ps": "349",
        "winner": "est"
    },
    {
        "centroid": [
            74.31110068604653,
            31.56233112870322
        ],
        "value": 806,
        "advantage": 0,
        "ps": "355",
        "winner": "est"
    },
    {
        "centroid": [
            74.28848955240073,
            31.56431808410196
        ],
        "value": 711,
        "advantage": 0,
        "ps": "356",
        "winner": "est"
    },
    {
        "centroid": [
            74.29548864475784,
            31.598865257325226
        ],
        "value": 273,
        "advantage": 0,
        "ps": "359",
        "winner": "est"
    },
    {
        "centroid": [
            74.28337138753862,
            31.571828980193846
        ],
        "value": 469,
        "advantage": 0,
        "ps": "360",
        "winner": "est"
    },
    {
        "centroid": [
            74.29907101392497,
            31.568551231099537
        ],
        "value": 257,
        "advantage": 0,
        "ps": "361",
        "winner": "est"
    },
    {
        "centroid": [
            74.29052399871725,
            31.6004224490031
        ],
        "value": 928,
        "advantage": 0,
        "ps": "362",
        "winner": "pti"
    },
    {
        "centroid": [
            74.27719321158555,
            31.58834498830154
        ],
        "value": 542,
        "advantage": 0,
        "ps": "363",
        "winner": "pti"
    },
    {
        "centroid": [
            74.30423541205084,
            31.570475130780967
        ],
        "value": 1853,
        "advantage": 1000,
        "ps": "364",
        "winner": "est"
    },
    {
        "centroid": [
            74.30955952320365,
            31.557580151057287
        ],
        "value": 521,
        "advantage": 0,
        "ps": "365",
        "winner": "pti"
    },
    {
        "centroid": [
            74.32406370743902,
            31.55888513614188
        ],
        "value": 1948,
        "advantage": 1000,
        "ps": "366",
        "winner": "est"
    },
    {
        "centroid": [
            74.31029472687294,
            31.553488335972872
        ],
        "value": 763,
        "advantage": 1030,
        "ps": "370",
        "winner": "est"
    },
    {
        "centroid": [
            74.29902649831958,
            31.563431505577068
        ],
        "value": 525,
        "advantage": 0,
        "ps": "376",
        "winner": "pti"
    }
]